djangocms_meta_og/__init__.py
djangocms_meta_og/apps.py
djangocms_meta_og/cms_toolbars.py
djangocms_meta_og/context_processors.py
djangocms_meta_og/dynamic_content.py
djangocms_meta_og/models.py
djangocms_meta_og/utils.py
djangocms_meta_og/admin/__init__.py
djangocms_meta_og/admin/fields.py
djangocms_meta_og/admin/forms.py
djangocms_meta_og/admin/options.py
djangocms_meta_og/locale/cs/LC_MESSAGES/django.mo
djangocms_meta_og/locale/cs/LC_MESSAGES/django.po
djangocms_meta_og/locale/cs/LC_MESSAGES/djangojs.mo
djangocms_meta_og/locale/cs/LC_MESSAGES/djangojs.po
djangocms_meta_og/migrations/0001_initial.py
djangocms_meta_og/migrations/__init__.py
djangocms_meta_og/static/djangocms_meta_og/css/admin.css
djangocms_meta_og/static/djangocms_meta_og/js/admin.js
djangocms_meta_og/templates/admin/djangocms_meta_og/pagemetaog/change_form.html
djangocms_meta_og/templatetags/__init__.py
djangocms_meta_og/templatetags/djangocms_meta_og.py
djangocms_meta_og/tests/__init__.py
djangocms_meta_og/tests/settings.py
djangocms_meta_og/tests/test_context_processors.py
djangocms_meta_og/tests/test_models.py
djangocms_meta_og/tests/test_templatetags.py
djangocms_meta_og/tests/templates/page.html
djangocms_meta_og-2.0.1.dist-info/METADATA
djangocms_meta_og-2.0.1.dist-info/WHEEL
djangocms_meta_og-2.0.1.dist-info/top_level.txt
djangocms_meta_og-2.0.1.dist-info/RECORD
