Metadata-Version: 2.2
Name: djangocms-meta-og
Version: 2.0.1
Summary: DjangoCMS HTML Meta tags for OpenGraph.
Author-email: Zdeněk Böhm <zdenek.bohm@nic.cz>
License: BSD License
Project-URL: Homepage, https://gitlab.nic.cz/djangocms-apps/djangocms-meta-og
Project-URL: Repository, https://gitlab.nic.cz/djangocms-apps/djangocms-meta-og.git
Classifier: Development Status :: 5 - Production/Stable
Classifier: Environment :: Web Environment
Classifier: Intended Audience :: Developers
Classifier: License :: OSI Approved :: BSD License
Classifier: Operating System :: OS Independent
Classifier: Programming Language :: Python :: 3
Classifier: Programming Language :: Python :: 3.9
Classifier: Programming Language :: Python :: 3.10
Classifier: Programming Language :: Python :: 3.11
Classifier: Programming Language :: Python :: 3.12
Classifier: Framework :: Django CMS
Classifier: Framework :: Django CMS :: 3.4
Classifier: Framework :: Django CMS :: 4.1
Classifier: Topic :: Internet :: WWW/HTTP
Classifier: Topic :: Internet :: WWW/HTTP :: Dynamic Content
Classifier: Topic :: Software Development
Classifier: Topic :: Software Development :: Libraries
Classifier: Topic :: Software Development :: Libraries :: Application Frameworks
Requires-Python: >=3.9
Requires-Dist: django-cms
Requires-Dist: django-meta-og~=2.0
Provides-Extra: test
Requires-Dist: easy-thumbnails; extra == "test"
Requires-Dist: django-filer; extra == "test"
